{"field": "O3Removal", "classificationMethod": "esriClassifyQuantile", "classBreakInfos": [{"classMaxValue": 959.648395382999, "symbol": {"color": [255, 255, 128, 255], "style": "esriSFSSolid", "type": "esriSFS", "outline": {"color": [110, 110, 110, 255], "width": 1, "style": "esriSLSSolid", "type": "esriSLS"}}, "description": "", "label": "1 - 960"}, {"classMaxValue": 1656.09370441, "symbol": {"color": [113, 235, 47, 255], "style": "esriSFSSolid", "type": "esriSFS", "outline": {"color": [110, 110, 110, 255], "width": 1, "style": "esriSLSSolid", "type": "esriSLS"}}, "description": "", "label": "961 - 1,656"}, {"classMaxValue": 2858.23972998999, "symbol": {"color": [61, 184, 104, 255], "style": "esriSFSSolid", "type": "esriSFS", "outline": {"color": [110, 110, 110, 255], "width": 1, "style": "esriSLSSolid", "type": "esriSLS"}}, "description": "", "label": "1,657 - 2,858"}, {"classMaxValue": 6965.38746351, "symbol": {"color": [33, 110, 158, 255], "style": "esriSFSSolid", "type": "esriSFS", "outline": {"color": [110, 110, 110, 255], "width": 1, "style": "esriSLSSolid", "type": "esriSLS"}}, "description": "", "label": "2,859 - 6,965"}, {"classMaxValue": 159715.0, "symbol": {"color": [12, 16, 120, 255], "style": "esriSFSSolid", "type": "esriSFS", "outline": {"color": [110, 110, 110, 255], "width": 1, "style": "esriSLSSolid", "type": "esriSLS"}}, "description": "", "label": "6,966 - 159,714"}], "type": "classBreaks", "minValue": 0.0}