{"field": "O3_Acute_Respiratory_Symptoms_I", "classificationMethod": "esriClassifyQuantile", "classBreakInfos": [{"classMaxValue": 0.436871025636574, "symbol": {"color": [255, 255, 128, 255], "style": "esriSFSSolid", "type": "esriSFS", "outline": {"color": [110, 110, 110, 255], "width": 1, "style": "esriSLSSolid", "type": "esriSLS"}}, "description": "", "label": "0.000 - 0.437"}, {"classMaxValue": 0.787388235, "symbol": {"color": [113, 235, 47, 255], "style": "esriSFSSolid", "type": "esriSFS", "outline": {"color": [110, 110, 110, 255], "width": 1, "style": "esriSLSSolid", "type": "esriSLS"}}, "description": "", "label": "0.438 - 0.787"}, {"classMaxValue": 1.25395715674928, "symbol": {"color": [61, 184, 104, 255], "style": "esriSFSSolid", "type": "esriSFS", "outline": {"color": [110, 110, 110, 255], "width": 1, "style": "esriSLSSolid", "type": "esriSLS"}}, "description": "", "label": "0.788 - 1.254"}, {"classMaxValue": 2.10713437283479, "symbol": {"color": [33, 110, 158, 255], "style": "esriSFSSolid", "type": "esriSFS", "outline": {"color": [110, 110, 110, 255], "width": 1, "style": "esriSLSSolid", "type": "esriSLS"}}, "description": "", "label": "1.255 - 2.107"}, {"classMaxValue": 41.0, "symbol": {"color": [12, 16, 120, 255], "style": "esriSFSSolid", "type": "esriSFS", "outline": {"color": [110, 110, 110, 255], "width": 1, "style": "esriSLSSolid", "type": "esriSLS"}}, "description": "", "label": "2.108 - 40.869"}], "type": "classBreaks", "minValue": 0.0}