{"field": "O3_Mortality_V", "classificationMethod": "esriClassifyQuantile", "classBreakInfos": [{"classMaxValue": 1078.7778364006, "symbol": {"color": [255, 255, 128, 255], "style": "esriSFSSolid", "type": "esriSFS", "outline": {"color": [110, 110, 110, 255], "width": 1, "style": "esriSLSSolid", "type": "esriSLS"}}, "description": "", "label": "0 - 1,079"}, {"classMaxValue": 1773.50025909604, "symbol": {"color": [113, 235, 47, 255], "style": "esriSFSSolid", "type": "esriSFS", "outline": {"color": [110, 110, 110, 255], "width": 1, "style": "esriSLSSolid", "type": "esriSLS"}}, "description": "", "label": "1,080 - 1,774"}, {"classMaxValue": 2511.69828799142, "symbol": {"color": [61, 184, 104, 255], "style": "esriSFSSolid", "type": "esriSFS", "outline": {"color": [110, 110, 110, 255], "width": 1, "style": "esriSLSSolid", "type": "esriSLS"}}, "description": "", "label": "1,775 - 2,512"}, {"classMaxValue": 3653.36781873925, "symbol": {"color": [33, 110, 158, 255], "style": "esriSFSSolid", "type": "esriSFS", "outline": {"color": [110, 110, 110, 255], "width": 1, "style": "esriSLSSolid", "type": "esriSLS"}}, "description": "", "label": "2,513 - 3,653"}, {"classMaxValue": 25383.0, "symbol": {"color": [12, 16, 120, 255], "style": "esriSFSSolid", "type": "esriSFS", "outline": {"color": [110, 110, 110, 255], "width": 1, "style": "esriSLSSolid", "type": "esriSLS"}}, "description": "", "label": "3,654 - 25,383"}], "type": "classBreaks", "minValue": 0.0}