{"field": "SO2_Asthma_Exacerbation_I", "classificationMethod": "esriClassifyQuantile", "classBreakInfos": [{"classMaxValue": 0.0242147674109877, "symbol": {"color": [255, 255, 128, 255], "style": "esriSFSSolid", "type": "esriSFS", "outline": {"color": [110, 110, 110, 255], "width": 1, "style": "esriSLSSolid", "type": "esriSLS"}}, "description": "", "label": "0.000 - 0.024"}, {"classMaxValue": 0.0360079508639973, "symbol": {"color": [113, 235, 47, 255], "style": "esriSFSSolid", "type": "esriSFS", "outline": {"color": [110, 110, 110, 255], "width": 1, "style": "esriSLSSolid", "type": "esriSLS"}}, "description": "", "label": "0.025 - 0.036"}, {"classMaxValue": 0.0483462703099619, "symbol": {"color": [61, 184, 104, 255], "style": "esriSFSSolid", "type": "esriSFS", "outline": {"color": [110, 110, 110, 255], "width": 1, "style": "esriSLSSolid", "type": "esriSLS"}}, "description": "", "label": "0.037 - 0.048"}, {"classMaxValue": 0.0659668604388212, "symbol": {"color": [33, 110, 158, 255], "style": "esriSFSSolid", "type": "esriSFS", "outline": {"color": [110, 110, 110, 255], "width": 1, "style": "esriSLSSolid", "type": "esriSLS"}}, "description": "", "label": "0.049 - 0.066"}, {"classMaxValue": 0.23392208782618, "symbol": {"color": [12, 16, 120, 255], "style": "esriSFSSolid", "type": "esriSFS", "outline": {"color": [110, 110, 110, 255], "width": 1, "style": "esriSLSSolid", "type": "esriSLS"}}, "description": "", "label": "0.067 - 0.234"}], "type": "classBreaks", "minValue": 0.0}