{"field": "CODmean", "classificationMethod": "esriClassifyQuantile", "classBreakInfos": [{"classMaxValue": 17.759229, "symbol": {"color": [255, 255, 128, 255], "style": "esriSFSSolid", "type": "esriSFS", "outline": {"color": [110, 110, 110, 255], "width": 1, "style": "esriSLSSolid", "type": "esriSLS"}}, "description": "", "label": "1 - 18"}, {"classMaxValue": 31.319671, "symbol": {"color": [113, 235, 47, 255], "style": "esriSFSSolid", "type": "esriSFS", "outline": {"color": [110, 110, 110, 255], "width": 1, "style": "esriSLSSolid", "type": "esriSLS"}}, "description": "", "label": "19 - 31"}, {"classMaxValue": 55.294587, "symbol": {"color": [61, 184, 104, 255], "style": "esriSFSSolid", "type": "esriSFS", "outline": {"color": [110, 110, 110, 255], "width": 1, "style": "esriSLSSolid", "type": "esriSLS"}}, "description": "", "label": "32 - 55"}, {"classMaxValue": 121.71442, "symbol": {"color": [33, 110, 158, 255], "style": "esriSFSSolid", "type": "esriSFS", "outline": {"color": [110, 110, 110, 255], "width": 1, "style": "esriSLSSolid", "type": "esriSLS"}}, "description": "", "label": "56 - 122"}, {"classMaxValue": 1713.0, "symbol": {"color": [12, 16, 120, 255], "style": "esriSFSSolid", "type": "esriSFS", "outline": {"color": [110, 110, 110, 255], "width": 1, "style": "esriSLSSolid", "type": "esriSLS"}}, "description": "", "label": "123 - 1,713"}], "type": "classBreaks", "minValue": 1.0}