{"classificationMethod": "esriClassifyQuantile", "backgroundFillSymbol": {"color": [0, 0, 0, 0], "style": "esriSFSSolid", "type": "esriSFS", "outline": {"color": [0, 0, 0, 0], "width": 0.4, "style": "esriSLSSolid", "type": "esriSLS"}}, "minValue": 9.0, "field": "under_13", "classBreakInfos": [{"classMaxValue": 197.0, "symbol": {"style": "esriSMSCircle", "angle": 0, "outline": {"color": [0, 0, 0, 255], "width": 1}, "color": [230, 152, 0, 255], "yoffset": 0, "type": "esriSMS", "xoffset": 0, "size": 4}, "desciption": "", "label": "9 - 197"}, {"classMaxValue": 252.0, "symbol": {"style": "esriSMSCircle", "angle": 0, "outline": {"color": [0, 0, 0, 255], "width": 1}, "color": [230, 152, 0, 255], "yoffset": 0, "type": "esriSMS", "xoffset": 0, "size": 7}, "desciption": "", "label": "198 - 252"}, {"classMaxValue": 330.0, "symbol": {"style": "esriSMSCircle", "angle": 0, "outline": {"color": [0, 0, 0, 255], "width": 1}, "color": [230, 152, 0, 255], "yoffset": 0, "type": "esriSMS", "xoffset": 0, "size": 10}, "desciption": "", "label": "253 - 330"}, {"classMaxValue": 651.0, "symbol": {"style": "esriSMSCircle", "angle": 0, "outline": {"color": [0, 0, 0, 255], "width": 1}, "color": [230, 152, 0, 255], "yoffset": 0, "type": "esriSMS", "xoffset": 0, "size": 13}, "desciption": "", "label": "331 - 651"}], "type": "classBreaks"}